islet/__init__.py
islet/main.py
islet/utils.py
islet/tests/__init__.py
islet-0.0.2.dist-info/LICENSE
islet-0.0.2.dist-info/METADATA
islet-0.0.2.dist-info/WHEEL
islet-0.0.2.dist-info/top_level.txt
islet-0.0.2.dist-info/RECORD
