Metadata-Version: 2.1
Name: islet
Version: 0.0.2
Summary: A python key-value file database
Home-page: https://github.com/mullenkamp/islet
Author: Mike Kittridge
Author-email: mullenkamp1@gmail.com
License: Apache
Keywords: shelve dbm
Classifier: Development Status :: 3 - Alpha
Classifier: Intended Audience :: Developers
Classifier: License :: OSI Approved :: Apache Software License
Classifier: Programming Language :: Python :: 3.8
Classifier: Programming Language :: Python :: 3.9
License-File: LICENSE
